{
    "gachiAstrology": {
        "title": "Gachimuchi Astrology",
        "href": "https://vk.com/gachiastro",
        "logo": "https://sun9-24.userapi.com/impf/c846419/v846419582/1c20a5/5j5a6kcTKAA.jpg?size=1100x1080&quality=96&sign=8add410f6f6cd229a7347629550b1b0d&type=album"
    },
    "reddit": {
        "title": "Reddit",
        "href": "https://vk.com/reddit",
        "logo": "https://sun1-26.userapi.com/impf/c831309/v831309010/1723ee/0NBy-lypKYY.jpg?size=1200x1200&quality=96&sign=26399360bdeb2aebdf6463d244b058a1&type=album"
    },
    "chudesaRF": {
        "title": "чудеса рф",
        "href": "https://vk.com/chudesa_rf",
        "logo": "https://sun1-47.userapi.com/impf/c846320/v846320673/11a262/BupOSRpLBkE.jpg?size=1182x1182&quality=96&sign=183843d2e05828d5d108d9ebba0560f1&type=album"
    },
    "amdevs": {
        "title": "абстрактные мемы для элиты всех сортов | АМДЭВС",
        "href": "https://vk.com/abstract_memes",
        "logo": "https://sun1-19.userapi.com/impf/c637622/v637622257/5b5bf/xjT2gn-8MU4.jpg?size=2159x2160&quality=96&sign=0b6b5db7172717d17282b085ed4360b8&type=album"
    },
    "cyberpank": {
        "title": "киберпанк, который мы заслужили",
        "href": "https://vk.com/futureisnow",
        "logo": "https://sun9-20.userapi.com/impf/c845124/v845124938/4b86f/VEkt3wkafhU.jpg?size=604x576&quality=96&sign=eba5f143c420008f19033df2039c41d1&type=album"
    },
    "kalik": {
        "title": "Калик)",
        "href": "https://vk.com/kalikfan",
        "logo": "https://sun9-43.userapi.com/impf/c851324/v851324288/1f0c37/ha0hQs3Sboo.jpg?size=750x743&quality=96&sign=832dccfd376ddb8aff3e82ab5268cf69&type=album"
    },
    "humoreski": {
        "title": "Мои любимые юморески",
        "href": "https://vk.com/jumoreski",
        "logo": "https://sun1-24.userapi.com/impf/c851020/v851020750/1afa66/3olagiqd6XY.jpg?size=800x800&quality=96&sign=07da0e49cf7bc2bbd38f5e7ecde2aa69&type=album"
    },
    "beobanka": {
        "title": "The Church of St. Beobanka",
        "href": "https://vk.com/saintbeobanka",
        "logo": "https://sun1-18.userapi.com/impf/c851128/v851128805/182b8e/aMyHPALu2Hw.jpg?size=1000x800&quality=96&sign=88b7342bba88b740cf6bd9062688e783&type=album"
    },
    "swipeRight": {
        "title": "Swipe Right",
        "href": "https://vk.com/swiperight",
        "logo": "https://sun9-24.userapi.com/impf/c850436/v850436840/18c1f7/D0LWmnCQnmE.jpg?size=2000x2000&quality=96&sign=5036002f2a280095b914d46d44cdcc57&type=album"
    },
    "altRight": {
        "title": "Alt-Right",
        "href": "https://vk.com/alterright",
        "logo": "https://sun9-23.userapi.com/impf/c857628/v857628503/18d7a8/tBj0PmnAYfk.jpg?size=1926x1923&quality=96&sign=d53365b0c925bcc55c6682daeca05924&type=album"
    },
    "ebanyPhisics": {
        "title": "Физика для ебанов",
        "href": "https://vk.com/ebanphysics",
        "logo": "https://sun1-29.userapi.com/impf/c854028/v854028338/d3b31/R-E_TSrv2SU.jpg?size=1827x1104&quality=96&sign=c641760d00474a16492ed6680094c4e0&type=album"
    },
    "manOfCulture": {
        "title": "Это не нервы, я мужчина-стерва.",
        "href": "https://vk.com/bitchy_man",
        "logo": "https://sun9-32.userapi.com/impg/cXiSnRbPRUkv0WbbraoOJfW7qs36FuxRzgcUFw/_txSek6eCgs.jpg?size=1140x1295&quality=96&sign=dc995bf06b935ae138ec79902fdc3097&type=album"
    }
}